{"user_id":6,"id":9,"title":"hello world","welcomeMessage":"","regDate":"2019-6-1 13:32:13","questionsArray":[{"id":1,"body":"kjl;kkj","isRequired":false,"answerType":"textbox","answers":""},{"id":2,"body":"sdfgcfhg","isRequired":false,"answerType":"mulchoice","answers":[{"body":"1"},{"body":"13"},{"body":"134"}]},{"id":3,"body":"sdfsdfsdf","isRequired":false,"answerType":"checkbox","answers":[{"body":"h"},{"body":"hr"},{"body":"hrt"}]},{"id":4,"body":"sdfvywdf","isRequired":false,"answerType":"essay"},{"id":5,"body":"ukjjncwde","isRequired":false,"answerType":"scale","answers":{"min":"0","max":"10","step":"1","value":0}},{"id":6,"body":"de;l,;ds","isRequired":false,"answerType":"date"}]}